fa_common/__init__.py
fa_common/auth/__init__.py
fa_common/auth/enums.py
fa_common/auth/models.py
fa_common/auth/utils.py
fa_common/config.py
fa_common/db/__init__.py
fa_common/db/utils.py
fa_common/enums.py
fa_common/exception_handlers.py
fa_common/exceptions.py
fa_common/licence/__init__.py
fa_common/licence/models.py
fa_common/licence/utils.py
fa_common/models.py
fa_common/responses.py
fa_common/routes/__init__.py
fa_common/routes/dataset/__init__.py
fa_common/routes/dataset/models.py
fa_common/routes/dataset/routes.py
fa_common/routes/dataset/service.py
fa_common/routes/dataset/utils.py
fa_common/routes/files/__init__.py
fa_common/routes/files/models.py
fa_common/routes/files/routes.py
fa_common/routes/files/service.py
fa_common/routes/files/utils.py
fa_common/routes/modules/__init__.py
fa_common/routes/modules/enums.py
fa_common/routes/modules/models.py
fa_common/routes/modules/routes.py
fa_common/routes/modules/service.py
fa_common/routes/modules/types.py
fa_common/routes/modules/utils.py
fa_common/routes/notification/__init__.py
fa_common/routes/notification/enums.py
fa_common/routes/notification/models.py
fa_common/routes/notification/service.py
fa_common/routes/project/__init__.py
fa_common/routes/project/models.py
fa_common/routes/project/routes.py
fa_common/routes/project/service.py
fa_common/routes/shared/__init__.py
fa_common/routes/shared/models.py
fa_common/routes/tables/__init__.py
fa_common/routes/tables/models.py
fa_common/routes/tables/routes.py
fa_common/routes/tables/service.py
fa_common/routes/user/__init__.py
fa_common/routes/user/models.py
fa_common/routes/user/routes.py
fa_common/routes/user/service.py
fa_common/routes/user/types.py
fa_common/routes/user/utils.py
fa_common/routes/workflow/__init__.py
fa_common/routes/workflow/models.py
fa_common/routes/workflow/routes.py
fa_common/routes/workflow/service.py
fa_common/routes/workflow/types.py
fa_common/storage/__init__.py
fa_common/storage/base_client.py
fa_common/storage/localfs_client.py
fa_common-4.3.0.dist-info/LICENSE.txt
fa_common-4.3.0.dist-info/METADATA
fa_common-4.3.0.dist-info/WHEEL
fa_common-4.3.0.dist-info/RECORD
